odoo/addons/l10n_es_aeat_partner_check/README.rst
odoo/addons/l10n_es_aeat_partner_check/__init__.py
odoo/addons/l10n_es_aeat_partner_check/__manifest__.py
odoo/addons/l10n_es_aeat_partner_check/i18n/ca.po
odoo/addons/l10n_es_aeat_partner_check/i18n/es.po
odoo/addons/l10n_es_aeat_partner_check/i18n/l10n_es_aeat_partner_check.pot
odoo/addons/l10n_es_aeat_partner_check/models/__init__.py
odoo/addons/l10n_es_aeat_partner_check/models/res_company.py
odoo/addons/l10n_es_aeat_partner_check/models/res_config_settings.py
odoo/addons/l10n_es_aeat_partner_check/models/res_partner.py
odoo/addons/l10n_es_aeat_partner_check/readme/CONTRIBUTORS.md
odoo/addons/l10n_es_aeat_partner_check/readme/DESCRIPTION.md
odoo/addons/l10n_es_aeat_partner_check/readme/INSTALL.md
odoo/addons/l10n_es_aeat_partner_check/readme/USAGE.md
odoo/addons/l10n_es_aeat_partner_check/static/description/icon.png
odoo/addons/l10n_es_aeat_partner_check/static/description/index.html
odoo/addons/l10n_es_aeat_partner_check/tests/__init__.py
odoo/addons/l10n_es_aeat_partner_check/tests/test_res_partner.py
odoo/addons/l10n_es_aeat_partner_check/views/res_company_view.xml
odoo/addons/l10n_es_aeat_partner_check/views/res_config_settings_view.xml
odoo/addons/l10n_es_aeat_partner_check/views/res_partner_view.xml
odoo_addon_l10n_es_aeat_partner_check-18.0.1.0.0.2.dist-info/METADATA
odoo_addon_l10n_es_aeat_partner_check-18.0.1.0.0.2.dist-info/WHEEL
odoo_addon_l10n_es_aeat_partner_check-18.0.1.0.0.2.dist-info/top_level.txt
odoo_addon_l10n_es_aeat_partner_check-18.0.1.0.0.2.dist-info/RECORD
