Metadata-Version: 2.1
Name: odoo-addon-l10n_es_aeat_partner_check
Version: 18.0.1.0.0.2
Requires-Python: >=3.10
Requires-Dist: odoo-addon-l10n_es_aeat==18.0.*
Requires-Dist: odoo==18.0.*
Summary: =?utf-8?q?AEAT_-_Comprobaci=C3=B3n_de_Calidad_de_datos_identificativos?=
Home-page: https://github.com/OCA/l10n-spain
License: AGPL-3
Author: Acysos S.L., Odoo Community Association (OCA)
Author-email: support@odoo-community.org
Classifier: Programming Language :: Python
Classifier: Framework :: Odoo
Classifier: Framework :: Odoo :: 18.0
Classifier: License :: OSI Approved :: GNU Affero General Public License v3
